LICENSE
MANIFEST.in
README.md
VERSION
setup.cfg
setup.py
src/sparse/__init__.py
src/sparse/browser.py
src/sparse/config.py
src/sparse/interpolate.py
src/sparse/main.py
src/sparse/validators.py
src/sparse/resources/__init__.py
src/sparse/resources/auth.py
src/sparse_cli.egg-info/PKG-INFO
src/sparse_cli.egg-info/SOURCES.txt
src/sparse_cli.egg-info/dependency_links.txt
src/sparse_cli.egg-info/entry_points.txt
src/sparse_cli.egg-info/not-zip-safe
src/sparse_cli.egg-info/requires.txt
src/sparse_cli.egg-info/top_level.txt
test/test_main.py