Metadata-Version: 2.1
Name: sparse-cli
Version: 0.0.1
Summary: Sparse command line utility.
Home-page: https://github.com/sparse-data/sparse-cli
Author: Sparse
Author-email: info@sparsedata.net
License: MIT
Platform: UNKNOWN
Classifier: Intended Audience :: Developers
Classifier: License :: OSI Approved :: MIT License
Classifier: Programming Language :: Python :: 3
Requires-Python: >=3.5
License-File: LICENSE
